pytorch_estimator/__init__.py
pytorch_estimator/init.py
pytorch_estimator/losses.py
pytorch_estimator/lr_schedulers.py
pytorch_estimator/optimizers.py
pytorch_estimator/samplers.py
pytorch_estimator/seed.py
pytorch_estimator/callbacks/__init__.py
pytorch_estimator/callbacks/base.py
pytorch_estimator/callbacks/checkpoint.py
pytorch_estimator/callbacks/history.py
pytorch_estimator/callbacks/progbar.py
pytorch_estimator/callbacks/tensorboard.py
pytorch_estimator/data/__init__.py
pytorch_estimator/estimator/__init__.py
pytorch_estimator/estimator/estimator.py
pytorch_estimator/metrics/__init__.py
pytorch_estimator/metrics/accuracy.py
pytorch_estimator/metrics/error.py
pytorch_estimator/metrics/loss.py
pytorch_estimator/metrics/metric.py
pytorch_estimator/metrics/regression/__init__.py
pytorch_estimator/metrics/regression/pearson.py
pytorch_estimator/metrics/regression/spearman.py
pytorch_estimator/models/__init__.py
pytorch_estimator/models/cnn.py
pytorch_estimator/models/simple_mlp.py
pytorch_estimator/modules/__init__.py
pytorch_estimator/modules/pool.py
pytorch_estimator/testing/__init__.py
pytorch_estimator/testing/models.py
pytorch_estimator-0.3.1.dist-info/METADATA
pytorch_estimator-0.3.1.dist-info/WHEEL
pytorch_estimator-0.3.1.dist-info/top_level.txt
pytorch_estimator-0.3.1.dist-info/RECORD
